walt/__init__.py
walt/doc/__init__.py
walt/doc/color.py
walt/doc/markdown.py
walt/doc/mdtable.py
walt/doc/pager.py
walt/doc/html/.buildinfo
walt/doc/html/__init__.py
walt/doc/html/admin.html
walt/doc/html/boot-modes.html
walt/doc/html/client-install.html
walt/doc/html/compatibility.html
walt/doc/html/design-notes.html
walt/doc/html/dev-client.html
walt/doc/html/dev-server-db.html
walt/doc/html/dev-server.html
walt/doc/html/dev-walt-python-packages.html
walt/doc/html/developer.html
walt/doc/html/device-config.html
walt/doc/html/device-expose.html
walt/doc/html/device-netsetup.html
walt/doc/html/device-port-config.html
walt/doc/html/device-sets.html
walt/doc/html/g5k.html
walt/doc/html/genindex.html
walt/doc/html/image-build.html
walt/doc/html/image-cp.html
walt/doc/html/image-from-scratch.html
walt/doc/html/image-spec-file.html
walt/doc/html/index.html
walt/doc/html/log-cat.html
walt/doc/html/log-checkpoint.html
walt/doc/html/log-echo.html
walt/doc/html/log-format.html
walt/doc/html/log-history.html
walt/doc/html/log-issuers.html
walt/doc/html/log-monitor.html
walt/doc/html/log-realtime.html
walt/doc/html/log-show.html
walt/doc/html/log-tee.html
walt/doc/html/log-wait.html
walt/doc/html/logging.html
walt/doc/html/networking.html
walt/doc/html/new-node-support.html
walt/doc/html/node-bootup.html
walt/doc/html/node-config.html
walt/doc/html/node-console.html
walt/doc/html/node-cp.html
walt/doc/html/node-expose.html
walt/doc/html/node-install.html
walt/doc/html/node-netsetup.html
walt/doc/html/node-ownership.html
walt/doc/html/node-reboot.html
walt/doc/html/node-save.html
walt/doc/html/objects.inv
walt/doc/html/optional-features.html
walt/doc/html/packaging.html
walt/doc/html/registries.html
walt/doc/html/rpi-serial.html
walt/doc/html/scripting-images.html
walt/doc/html/scripting-logs.html
walt/doc/html/scripting-nodes.html
walt/doc/html/scripting-tools.html
walt/doc/html/scripting.html
walt/doc/html/search.html
walt/doc/html/searchindex.js
walt_doc-10.0.dist-info/METADATA
walt_doc-10.0.dist-info/WHEEL
walt_doc-10.0.dist-info/top_level.txt
walt_doc-10.0.dist-info/RECORD
